devbot_sa/__init__.py
devbot_sa/devbot.py
devbot_sa/devbot_assistant.py
devbot_sa/gui.py
devbot_sa/pdfGenerator.py
devbot_sa/prompts.py
devbot_sa-0.1.0.dist-info/METADATA
devbot_sa-0.1.0.dist-info/WHEEL
devbot_sa-0.1.0.dist-info/entry_points.txt
devbot_sa-0.1.0.dist-info/top_level.txt
devbot_sa-0.1.0.dist-info/RECORD
