Metadata-Version: 2.4
Name: devbot_sa
Version: 0.1.0
Summary: A developer assistant bot
Author-email: Hashim Khan <hashimahmedkhan2002@gmail.com>
Requires-Python: >=3.8
Requires-Dist: langchain==0.3.25
Requires-Dist: nbconvert
Requires-Dist: python-dotenv==1.0.0
Requires-Dist: langchain-google-genai
Requires-Dist: langchain-groq==0.3.2
Requires-Dist: langchain-openai==0.3.16
Requires-Dist: uvicorn==0.25.0
Requires-Dist: customtkinter==5.2.2
Requires-Dist: plantuml
Requires-Dist: reportlab==4.4.0
Requires-Dist: networkx
Requires-Dist: numpy
Requires-Dist: scipy
